kikinzage/__init__.py
kikinzage/__main__.py
kikinzage/client/__init__.py
kikinzage/client/asyncio.py
kikinzage/client/base.py
kikinzage/client/default.py
kikinzage/client/errors.py
kikinzage/client/utils.py
kikinzage/models/__init__.py
kikinzage/models/adres.py
kikinzage/models/collectie.py
kikinzage/models/eigendomsinformatie.py
kikinzage/models/enum.py
kikinzage/models/generated.py
kikinzage/models/misc.py
kikinzage/models/persoon.py
kikinzage/models/product.py
kikinzage/models/stukken.py
kikinzage/models/zekerheid.py
kikinzage/py.typed
kadaster_kikinzage_client-0.3.0.dist-info/LICENSE
kadaster_kikinzage_client-0.3.0.dist-info/METADATA
kadaster_kikinzage_client-0.3.0.dist-info/WHEEL
kadaster_kikinzage_client-0.3.0.dist-info/entry_points.txt
kadaster_kikinzage_client-0.3.0.dist-info/RECORD
