Metadata-Version: 2.1
Name: kadaster-kikinzage-client
Version: 0.3.0
Summary:  Kadaster - KIK Inzage API Python client
Home-page: https://github.com/foarsitter/kadaster-kik-inzage-api-python-client
License: MIT
Author: Jelmer Draaijer
Author-email: info@jelmert.nl
Requires-Python: >=3.8.1
Classifier: Development Status :: 4 - Beta
Classifier: License :: OSI Approved :: MIT License
Classifier: Programming Language :: Python :: 3
Classifier: Programming Language :: Python :: 3.9
Classifier: Programming Language :: Python :: 3.10
Classifier: Programming Language :: Python :: 3.11
Requires-Dist: click (>=8.0.1)
Requires-Dist: httpx (>=0.24.1)
Requires-Dist: pydantic (>=2.0.1)
Requires-Dist: typing-extensions (>=4.6.3,<5.0.0)
Project-URL: Changelog, https://github.com/foarsitter/kadaster-kik-inzage-api-python-client/releases
Project-URL: Documentation, https://kadaster-kik-inzage-api-python-client.readthedocs.io
Project-URL: Repository, https://github.com/foarsitter/kadaster-kik-inzage-api-python-client
